LICENSE
README.md
setup.py
middleware_help_python.egg-info/PKG-INFO
middleware_help_python.egg-info/SOURCES.txt
middleware_help_python.egg-info/dependency_links.txt
middleware_help_python.egg-info/requires.txt
middleware_help_python.egg-info/top_level.txt
middleware_helper/__init__.py
middleware_helper/libs.py
middleware_helper/mysql.py
middleware_helper/network.py
middleware_helper/redis.py